Metadata-Version: 1.1
Name: wedge
Version: 0.1.0
Summary: BSEC SIIM-ACR Pneumothorax Segmentation Kaggle Challenge
Home-page: https://github.com/yngtodd/wedge
Author: Todd Young
Author-email: youngmt1@ornl.gov
License: MIT
Keywords: wedge
Platform: UNKNOWN
Classifier: Development Status :: 2 - Pre-Alpha
Classifier: Intended Audience :: Developers
Classifier: License :: OSI Approved :: MIT License
Classifier: Natural Language :: English
Classifier: Programming Language :: Python :: 3.6
Classifier: Programming Language :: Python :: Implementation :: PyPy
